Metadata-Version: 2.1
Name: alibabacloud-fc-open20210406
Version: 2.0.11
Summary: Alibaba Cloud FC-Open (20210406) SDK Library for Python
Home-page: https://github.com/aliyun/alibabacloud-python-sdk
Author: Alibaba Cloud SDK
Author-email: sdk-team@alibabacloud.com
License: Apache License 2.0
Keywords: alibabacloud,fc,open20210406
Platform: any
Classifier: Development Status :: 4 - Beta
Classifier: Intended Audience :: Developers
Classifier: License :: OSI Approved :: Apache Software License
Classifier: Programming Language :: Python
Classifier: Programming Language :: Python :: 3
Classifier: Programming Language :: Python :: 3.6
Classifier: Programming Language :: Python :: 3.7
Classifier: Programming Language :: Python :: 3.8
Classifier: Programming Language :: Python :: 3.9
Classifier: Topic :: Software Development
Requires-Python: >=3.6
Requires-Dist: alibabacloud-tea-util <1.0.0,>=0.3.11
Requires-Dist: alibabacloud-tea-openapi <1.0.0,>=0.3.8
Requires-Dist: alibabacloud-openapi-util <1.0.0,>=0.2.1
Requires-Dist: alibabacloud-endpoint-util <1.0.0,>=0.0.3
Requires-Dist: alibabacloud-credentials <1.0.0,>=0.3.1
Requires-Dist: requests <3.0.0,>=2.21.0
Requires-Dist: alibabacloud-gateway-fc-util <1.0.0,>=0.0.4
